{"updated":"2026-05-08T01:25:51.456243+00:00","source":"ENTSO-E Transparency Platform","corridors":{"PT\u2192ES":{"from":"PT","to":"ES","latest":{"time":"00:00","mw":0},"values":[{"time":"00:00","mw":0}]},"ES\u2192PT":{"from":"ES","to":"PT","latest":{"time":"04:00","mw":1940},"values":[{"time":"00:00","mw":1555},{"time":"01:00","mw":1773},{"time":"02:00","mw":2000},{"time":"03:00","mw":2019},{"time":"04:00","mw":1940}]},"ES\u2192FR":{"from":"ES","to":"FR","latest":{"time":"00:00","mw":0},"values":[{"time":"00:00","mw":0}]},"FR\u2192ES":{"from":"FR","to":"ES","latest":{"time":"04:00","mw":2950},"values":[{"time":"00:00","mw":2010},{"time":"01:00","mw":2214},{"time":"02:00","mw":2878},{"time":"03:00","mw":2776},{"time":"04:00","mw":2950}]},"FR\u2192DE":{"from":"FR","to":"DE","latest":{"time":"03:00","mw":1842},"values":[{"time":"00:00","mw":1648},{"time":"01:00","mw":1823},{"time":"02:00","mw":1897},{"time":"03:00","mw":1842}]},"DE\u2192FR":{"from":"DE","to":"FR","latest":{"time":"00:00","mw":0},"values":[{"time":"00:00","mw":0}]},"FR\u2192GB":{"from":"FR","to":"GB","latest":{"time":"00:00","mw":3062},"values":[{"time":"00:00","mw":3062}]},"GB\u2192FR":{"from":"GB","to":"FR","latest":{"time":"00:00","mw":0},"values":[{"time":"00:00","mw":0}]},"DE\u2192NL":{"from":"DE","to":"NL","latest":{"time":"00:00","mw":0},"values":[{"time":"00:00","mw":0}]},"NL\u2192DE":{"from":"NL","to":"DE","latest":{"time":"03:00","mw":1305},"values":[{"time":"00:00","mw":1769},{"time":"01:00","mw":1314},{"time":"02:00","mw":1308},{"time":"03:00","mw":1305}]},"DE\u2192AT":{"from":"DE","to":"AT","latest":{"time":"03:00","mw":165},"values":[{"time":"00:00","mw":188},{"time":"01:00","mw":165},{"time":"02:00","mw":174},{"time":"03:00","mw":165}]},"AT\u2192DE":{"from":"AT","to":"DE","latest":{"time":"03:00","mw":556},"values":[{"time":"00:00","mw":528},{"time":"01:00","mw":553},{"time":"02:00","mw":582},{"time":"03:00","mw":556}]},"FR\u2192IT":{"from":"FR","to":"IT","latest":{"time":"03:00","mw":3829},"values":[{"time":"00:00","mw":3857},{"time":"01:00","mw":3773},{"time":"02:00","mw":3785},{"time":"03:00","mw":3829}]},"IT\u2192FR":{"from":"IT","to":"FR","latest":{"time":"00:00","mw":0},"values":[{"time":"00:00","mw":0}]},"NL\u2192BE":{"from":"NL","to":"BE","latest":{"time":"00:00","mw":1514},"values":[{"time":"00:00","mw":1514}]},"BE\u2192NL":{"from":"BE","to":"NL","latest":{"time":"00:00","mw":0},"values":[{"time":"00:00","mw":0}]},"DE\u2192PL":{"from":"DE","to":"PL","latest":{"time":"02:00","mw":190},"values":[{"time":"00:00","mw":255},{"time":"01:00","mw":232},{"time":"02:00","mw":190}]},"PL\u2192DE":{"from":"PL","to":"DE","latest":{"time":"02:00","mw":504},"values":[{"time":"00:00","mw":444},{"time":"01:00","mw":462},{"time":"02:00","mw":504}]},"DE\u2192DK":{"from":"DE","to":"DK","latest":{"time":"00:00","mw":0},"values":[{"time":"00:00","mw":0}]},"DK\u2192DE":{"from":"DK","to":"DE","latest":{"time":"03:00","mw":1342},"values":[{"time":"00:00","mw":1431},{"time":"01:00","mw":1361},{"time":"02:00","mw":1382},{"time":"03:00","mw":1342}]},"NO\u2192DK":{"from":"NO","to":"DK","latest":{"time":"04:00","mw":1602},"values":[{"time":"00:00","mw":1586},{"time":"01:00","mw":1578},{"time":"02:00","mw":1574},{"time":"03:00","mw":1492},{"time":"04:00","mw":1602}]},"DK\u2192NO":{"from":"DK","to":"NO","latest":{"time":"00:00","mw":0},"values":[{"time":"00:00","mw":0}]},"SE\u2192FI":{"from":"SE","to":"FI","latest":{"time":"03:00","mw":40},"values":[{"time":"00:00","mw":41},{"time":"01:00","mw":40},{"time":"02:00","mw":40},{"time":"03:00","mw":40}]},"FI\u2192SE":{"from":"FI","to":"SE","latest":{"time":"00:00","mw":0},"values":[{"time":"00:00","mw":0}]},"SE\u2192DK":{"from":"SE","to":"DK","latest":{"time":"03:00","mw":710},"values":[{"time":"00:00","mw":699},{"time":"01:00","mw":714},{"time":"03:00","mw":710}]},"DK\u2192SE":{"from":"DK","to":"SE","latest":{"time":"00:00","mw":0},"values":[{"time":"00:00","mw":0}]},"NO\u2192GB":{"from":"NO","to":"GB","latest":{"time":"00:00","mw":0},"values":[{"time":"00:00","mw":0}]},"GB\u2192NO":{"from":"GB","to":"NO","latest":{"time":"04:00","mw":404},"values":[{"time":"00:00","mw":516},{"time":"01:00","mw":503},{"time":"02:00","mw":503},{"time":"03:00","mw":484},{"time":"04:00","mw":404}]},"AT\u2192HU":{"from":"AT","to":"HU","latest":{"time":"03:00","mw":405},"values":[{"time":"00:00","mw":367},{"time":"01:00","mw":361},{"time":"02:00","mw":379},{"time":"03:00","mw":405}]},"HU\u2192AT":{"from":"HU","to":"AT","latest":{"time":"00:00","mw":0},"values":[{"time":"00:00","mw":0}]},"HU\u2192RO":{"from":"HU","to":"RO","latest":{"time":"03:00","mw":234},"values":[{"time":"00:00","mw":197},{"time":"01:00","mw":212},{"time":"02:00","mw":219},{"time":"03:00","mw":234}]},"RO\u2192HU":{"from":"RO","to":"HU","latest":{"time":"00:00","mw":0},"values":[{"time":"00:00","mw":0}]},"RO\u2192BG":{"from":"RO","to":"BG","latest":{"time":"00:00","mw":0},"values":[{"time":"00:00","mw":0}]},"BG\u2192RO":{"from":"BG","to":"RO","latest":{"time":"00:00","mw":626},"values":[{"time":"00:00","mw":626}]},"EE\u2192FI":{"from":"EE","to":"FI","latest":{"time":"00:00","mw":0},"values":[{"time":"00:00","mw":0}]},"FI\u2192EE":{"from":"FI","to":"EE","latest":{"time":"03:00","mw":478},"values":[{"time":"00:00","mw":485},{"time":"01:00","mw":464},{"time":"02:00","mw":472},{"time":"03:00","mw":478}]},"EE\u2192LV":{"from":"EE","to":"LV","latest":{"time":"01:00","mw":231},"values":[{"time":"00:00","mw":243},{"time":"01:00","mw":231}]},"LV\u2192EE":{"from":"LV","to":"EE","latest":{"time":"00:00","mw":0},"values":[{"time":"00:00","mw":0}]},"LV\u2192LT":{"from":"LV","to":"LT","latest":{"time":"03:00","mw":26},"values":[{"time":"00:00","mw":21},{"time":"01:00","mw":2},{"time":"02:00","mw":9},{"time":"03:00","mw":26}]},"LT\u2192LV":{"from":"LT","to":"LV","latest":{"time":"00:00","mw":0},"values":[{"time":"00:00","mw":0}]},"LT\u2192PL":{"from":"LT","to":"PL","latest":{"time":"02:00","mw":55},"values":[{"time":"00:00","mw":116},{"time":"01:00","mw":71},{"time":"02:00","mw":55}]},"PL\u2192LT":{"from":"PL","to":"LT","latest":{"time":"00:00","mw":0},"values":[{"time":"00:00","mw":0}]}},"net":{"ES-PT":{"from":"ES","to":"PT","net_mw":1940},"ES-FR":{"from":"FR","to":"ES","net_mw":2950},"DE-FR":{"from":"FR","to":"DE","net_mw":1842},"FR-GB":{"from":"FR","to":"GB","net_mw":3062},"DE-NL":{"from":"NL","to":"DE","net_mw":1305},"AT-DE":{"from":"AT","to":"DE","net_mw":391},"FR-IT":{"from":"FR","to":"IT","net_mw":3829},"BE-NL":{"from":"NL","to":"BE","net_mw":1514},"DE-PL":{"from":"PL","to":"DE","net_mw":314},"DE-DK":{"from":"DK","to":"DE","net_mw":1342},"NO-SE":{"from":"NO","to":"SE","net_mw":0},"DK-NO":{"from":"NO","to":"DK","net_mw":1602},"FI-SE":{"from":"SE","to":"FI","net_mw":40},"DK-SE":{"from":"SE","to":"DK","net_mw":710},"GB-NO":{"from":"GB","to":"NO","net_mw":404},"AT-HU":{"from":"AT","to":"HU","net_mw":405},"HU-RO":{"from":"HU","to":"RO","net_mw":234},"BG-RO":{"from":"BG","to":"RO","net_mw":626},"BG-GR":{"from":"BG","to":"GR","net_mw":0},"EE-FI":{"from":"FI","to":"EE","net_mw":478},"EE-LV":{"from":"EE","to":"LV","net_mw":231},"LT-LV":{"from":"LV","to":"LT","net_mw":26},"LT-PL":{"from":"LT","to":"PL","net_mw":55},"LT-SE":{"from":"LT","to":"SE","net_mw":0}}}