{"updated":"2026-04-23T20:55:46.996795+00:00","date":"2024-04-28","source":"ENTSO-E Transparency Platform (backfilled)","zones":{"PT":{"mix":{"Fossil Gas":111.5,"Fossil Hard coal":0.0,"Hydro Pumped Storage":985.6999999999999,"Hydro Run-of-river":1822.3999999999999,"Hydro Water Reservoir":788.8000000000001,"Biomass":394.3,"Solar":0.1,"Wind Offshore":19.5,"Wind Onshore":1469.0,"Other":32.3},"total_mw":5623.6,"renewable_pct":79.9},"ES":{"mix":{"Hydro Pumped Storage":1664.0,"Biomass":488.0,"Fossil Brown coal/Lignite":0.0,"Fossil Coal-derived gas":0.0,"Fossil Gas":4472.0,"Fossil Hard coal":248.0,"Fossil Oil":68.0,"Other":8.0,"Geothermal":0.0,"Hydro Run-of-river":1208.0,"Hydro Water Reservoir":4080.0,"Marine":0.0,"Nuclear":4316.0,"Other renewable":72.0,"Solar":560.0,"Waste":192.0,"Wind Offshore":0.0,"Wind Onshore":4356.0},"total_mw":21732.0,"renewable_pct":49.5},"DE":{"mix":{"Hydro Pumped Storage":520.5,"Solar":3.63,"Wind Onshore":10139.1,"Biomass":4075.24,"Fossil Brown coal/Lignite":5922.77,"Fossil Coal-derived gas":635.88,"Fossil Gas":4654.48,"Fossil Hard coal":985.69,"Fossil Oil":335.08,"Geothermal":22.1,"Hydro Run-of-river":1861.83,"Hydro Water Reservoir":103.56,"Other renewable":78.83,"Waste":664.33,"Wind Offshore":4499.38,"Other":145.0},"total_mw":34647.4,"renewable_pct":60.0},"FR":{"mix":{"Biomass":377.0,"Fossil Gas":608.0,"Fossil Hard coal":0.0,"Fossil Oil":126.0,"Hydro Pumped Storage":3518.0,"Hydro Run-of-river":5795.0,"Hydro Water Reservoir":2146.0,"Nuclear":38571.0,"Solar":0.0,"Waste":167.0,"Wind Offshore":79.0,"Wind Onshore":2493.0},"total_mw":53880.0,"renewable_pct":20.2},"IT":{"mix":{"Hydro Pumped Storage":221.0,"Biomass":172.0,"Fossil Coal-derived gas":11.0,"Fossil Gas":3074.0,"Fossil Hard coal":0.0,"Fossil Oil":5.0,"Hydro Run-of-river":2695.0,"Hydro Water Reservoir":331.0,"Solar":0.0,"Waste":232.0,"Wind Onshore":145.0,"Other":924.0},"total_mw":7810.0,"renewable_pct":42.8},"NL":{"mix":{"Biomass":34.28,"Fossil Gas":1698.93,"Fossil Hard coal":361.36,"Hydro Run-of-river":0.0,"Nuclear":0.02,"Solar":1.46,"Waste":296.45,"Wind Offshore":1730.8600000000001,"Wind Onshore":614.26,"Other":2378.09},"total_mw":7115.710000000001,"renewable_pct":33.5},"BE":{"mix":{"Hydro Pumped Storage":64.2825,"Biomass":80.67,"Fossil Gas":944.18,"Fossil Oil":0.0,"Hydro Run-of-river":34.46,"Nuclear":3475.59,"Solar":0.0,"Waste":169.825,"Wind Offshore":713.595,"Wind Onshore":543.57,"Other":844.89},"total_mw":6871.0625,"renewable_pct":20.0},"AT":{"mix":{"Biomass":304.0,"Fossil Gas":175.2,"Fossil Hard coal":0.0,"Fossil Oil":0.0,"Geothermal":0.07,"Hydro Pumped Storage":108.8,"Hydro Run-of-river":3644.0,"Hydro Water Reservoir":256.8,"Other renewable":0.0,"Solar":0.0,"Waste":100.0,"Wind Onshore":1728.0,"Other":22.0},"total_mw":6338.87,"renewable_pct":93.6},"CH":{"mix":{"Hydro Pumped Storage":422.2,"Hydro Run-of-river":143.33,"Hydro Water Reservoir":539.83,"Nuclear":1674.65,"Solar":0.0,"Wind Onshore":9.18},"total_mw":2789.19,"renewable_pct":24.8},"PL":{"mix":{"Biomass":224.07,"Fossil Brown coal/Lignite":2508.53,"Fossil Coal-derived gas":59.54,"Fossil Gas":1328.22,"Fossil Hard coal":4513.65,"Fossil Oil":277.38,"Hydro Pumped Storage":0.0,"Hydro Run-of-river":207.68,"Hydro Water Reservoir":0.0,"Solar":0.0,"Wind Onshore":5017.13},"total_mw":14136.2,"renewable_pct":38.5},"FI":{"mix":{"Biomass":561.99,"Fossil Gas":127.1,"Fossil Hard coal":164.1,"Fossil Oil":0.0,"Other":376.3,"Hydro Run-of-river":1692.7,"Nuclear":1868.4,"Other renewable":1.9,"Solar":0.0,"Waste":35.4,"Wind Onshore":1513.7},"total_mw":6341.589999999999,"renewable_pct":59.5},"GR":{"mix":{"Fossil Brown coal/Lignite":0.0,"Fossil Gas":1089.0,"Fossil Oil":0.0,"Hydro Pumped Storage":0.0,"Hydro Water Reservoir":50.0,"Solar":0.0,"Wind Onshore":2915.0},"total_mw":4054.0,"renewable_pct":73.1},"IE":{"mix":{"Fossil Gas":1157.4799999999998,"Fossil Hard coal":108.85,"Fossil Oil":2.44,"Other":65.94,"Hydro Pumped Storage":0.0,"Hydro Run-of-river":82.64,"Wind Onshore":1058.12},"total_mw":2475.47,"renewable_pct":46.1},"RO":{"mix":{"Biomass":51.0,"Fossil Brown coal/Lignite":654.0,"Fossil Gas":424.0,"Fossil Hard coal":0.0,"Hydro Run-of-river":1388.0,"Hydro Water Reservoir":446.0,"Nuclear":1386.0,"Solar":0.0,"Wind Onshore":820.0},"total_mw":5169.0,"renewable_pct":52.3},"BG":{"mix":{"Biomass":21.03,"Fossil Brown coal/Lignite":707.55,"Fossil Gas":175.27,"Fossil Hard coal":43.87,"Hydro Pumped Storage":0.0,"Hydro Run-of-river":223.58,"Hydro Water Reservoir":8.77,"Nuclear":1958.4,"Solar":0.02,"Waste":3.31,"Wind Onshore":180.66},"total_mw":3322.46,"renewable_pct":13.1},"HU":{"mix":{"Fossil Oil":0.02,"Biomass":97.76,"Fossil Brown coal/Lignite":219.05,"Fossil Gas":384.23,"Fossil Hard coal":40.28,"Geothermal":0.85,"Hydro Run-of-river":12.21,"Hydro Water Reservoir":17.23,"Nuclear":1933.6,"Other renewable":14.26,"Solar":0.01,"Waste":7.56,"Wind Onshore":111.47,"Other":45.09},"total_mw":2883.6200000000003,"renewable_pct":8.8},"CZ":{"mix":{"Biomass":283.91,"Fossil Brown coal/Lignite":1633.39,"Fossil Coal-derived gas":0.0,"Fossil Gas":151.54,"Fossil Hard coal":0.0,"Fossil Oil":0.0,"Hydro Pumped Storage":0.0,"Hydro Run-of-river":137.53,"Hydro Water Reservoir":17.58,"Nuclear":2884.55,"Other renewable":274.07,"Solar":0.0,"Waste":21.67,"Wind Onshore":83.63,"Other":54.14},"total_mw":5542.01,"renewable_pct":14.4},"EE":{"mix":{"Biomass":36.0,"Fossil Coal-derived gas":61.0,"Fossil Gas":3.5,"Other":145.3,"Hydro Run-of-river":1.2,"Other renewable":0.6,"Solar":0.6,"Waste":15.9,"Wind Onshore":276.5},"total_mw":540.5999999999999,"renewable_pct":58.3},"LV":{"mix":{"Biomass":43.0,"Fossil Gas":0.0,"Hydro Run-of-river":1044.0,"Solar":0.0,"Wind Onshore":69.0,"Other":0.0},"total_mw":1156.0,"renewable_pct":100.0},"LT":{"mix":{"Biomass":31.4,"Fossil Gas":53.92,"Hydro Pumped Storage":0.0,"Hydro Run-of-river":24.83,"Solar":0.0,"Waste":84.55,"Wind Onshore":914.64,"Other":13.56},"total_mw":1122.8999999999999,"renewable_pct":86.5},"NO":{"mix":{"Biomass":0.0,"Fossil Gas":0.44,"Hydro Run-of-river":2389.65,"Hydro Water Reservoir":4210.01,"Waste":26.119999999999997,"Wind Onshore":1423.51,"Hydro Pumped Storage":0.79},"total_mw":8050.52,"renewable_pct":99.7},"SE":{"mix":{"Hydro Water Reservoir":3375.1800000000003,"Solar":0.27,"Wind Onshore":1740.81,"Other":599.7,"Fossil Gas":0.2,"Nuclear":4407.0},"total_mw":10123.16,"renewable_pct":50.5},"DK":{"mix":{"Biomass":341.78,"Fossil Gas":159.82999999999998,"Fossil Hard coal":157.57999999999998,"Fossil Oil":30.62,"Hydro Run-of-river":2.28,"Other renewable":0.9,"Solar":0.12,"Waste":82.96,"Wind Offshore":2225.84,"Wind Onshore":2441.8700000000003},"total_mw":5443.780000000001,"renewable_pct":92.1}}}