{"updated":"2026-04-22T17:28:14.737123+00:00","date":"2025-07-17","source":"ENTSO-E Transparency Platform (backfilled)","endpoint":"https://web-api.tp.entsoe.eu/api","zones":{"PT":{"eic":"10YPT-REN------W","prices":[{"time":"22:00","hour":0,"price":119.78},{"time":"23:00","hour":1,"price":115.13},{"time":"00:00","hour":2,"price":113.84},{"time":"01:00","hour":3,"price":108.62},{"time":"03:00","hour":5,"price":113.46},{"time":"04:00","hour":6,"price":118.36},{"time":"05:00","hour":7,"price":125.0},{"time":"06:00","hour":8,"price":115.45},{"time":"07:00","hour":9,"price":104.27},{"time":"08:00","hour":10,"price":85.0},{"time":"09:00","hour":11,"price":77.07},{"time":"10:00","hour":12,"price":76.8},{"time":"11:00","hour":13,"price":76.68},{"time":"12:00","hour":14,"price":75.2},{"time":"13:00","hour":15,"price":73.0},{"time":"14:00","hour":16,"price":76.81},{"time":"15:00","hour":17,"price":84.36},{"time":"16:00","hour":18,"price":91.52},{"time":"17:00","hour":19,"price":108.66},{"time":"18:00","hour":20,"price":121.41},{"time":"19:00","hour":21,"price":128.67},{"time":"20:00","hour":22,"price":129.85},{"time":"21:00","hour":23,"price":120.76},{"time":"22:00","hour":0,"price":114.0},{"time":"23:00","hour":1,"price":107.61},{"time":"00:00","hour":2,"price":107.22},{"time":"01:00","hour":3,"price":105.9},{"time":"02:00","hour":4,"price":105.0},{"time":"03:00","hour":5,"price":107.17},{"time":"04:00","hour":6,"price":111.55},{"time":"05:00","hour":7,"price":115.14},{"time":"06:00","hour":8,"price":109.39},{"time":"07:00","hour":9,"price":90.64},{"time":"08:00","hour":10,"price":80.0},{"time":"09:00","hour":11,"price":81.58},{"time":"10:00","hour":12,"price":80.0},{"time":"11:00","hour":13,"price":73.02},{"time":"12:00","hour":14,"price":71.2},{"time":"13:00","hour":15,"price":72.68},{"time":"14:00","hour":16,"price":72.81},{"time":"15:00","hour":17,"price":72.8},{"time":"16:00","hour":18,"price":71.08},{"time":"17:00","hour":19,"price":72.8},{"time":"18:00","hour":20,"price":110.0},{"time":"19:00","hour":21,"price":119.39},{"time":"20:00","hour":22,"price":119.19},{"time":"21:00","hour":23,"price":111.65}],"latest":{"time":"21:00","hour":23,"price":111.65},"avg":98.76,"min":71.08,"max":129.85},"ES":{"eic":"10YES-REE------0","prices":[{"time":"22:00","hour":0,"price":119.78},{"time":"23:00","hour":1,"price":115.13},{"time":"00:00","hour":2,"price":113.84},{"time":"01:00","hour":3,"price":108.62},{"time":"03:00","hour":5,"price":113.46},{"time":"04:00","hour":6,"price":118.36},{"time":"05:00","hour":7,"price":125.0},{"time":"06:00","hour":8,"price":115.45},{"time":"07:00","hour":9,"price":104.27},{"time":"08:00","hour":10,"price":85.0},{"time":"09:00","hour":11,"price":77.07},{"time":"10:00","hour":12,"price":76.8},{"time":"11:00","hour":13,"price":76.68},{"time":"12:00","hour":14,"price":75.2},{"time":"13:00","hour":15,"price":73.0},{"time":"14:00","hour":16,"price":76.81},{"time":"15:00","hour":17,"price":84.36},{"time":"16:00","hour":18,"price":91.52},{"time":"17:00","hour":19,"price":108.66},{"time":"18:00","hour":20,"price":121.41},{"time":"19:00","hour":21,"price":128.67},{"time":"20:00","hour":22,"price":129.85},{"time":"21:00","hour":23,"price":120.76},{"time":"22:00","hour":0,"price":114.0},{"time":"23:00","hour":1,"price":107.61},{"time":"00:00","hour":2,"price":107.22},{"time":"01:00","hour":3,"price":105.9},{"time":"02:00","hour":4,"price":105.0},{"time":"03:00","hour":5,"price":107.17},{"time":"04:00","hour":6,"price":111.55},{"time":"05:00","hour":7,"price":115.14},{"time":"06:00","hour":8,"price":109.39},{"time":"07:00","hour":9,"price":90.64},{"time":"08:00","hour":10,"price":80.0},{"time":"09:00","hour":11,"price":81.58},{"time":"10:00","hour":12,"price":80.0},{"time":"11:00","hour":13,"price":73.02},{"time":"12:00","hour":14,"price":71.2},{"time":"13:00","hour":15,"price":72.68},{"time":"14:00","hour":16,"price":72.81},{"time":"15:00","hour":17,"price":72.8},{"time":"16:00","hour":18,"price":71.08},{"time":"17:00","hour":19,"price":72.8},{"time":"18:00","hour":20,"price":110.0},{"time":"19:00","hour":21,"price":119.39},{"time":"20:00","hour":22,"price":119.19},{"time":"21:00","hour":23,"price":111.65}],"latest":{"time":"21:00","hour":23,"price":111.65},"avg":98.76,"min":71.08,"max":129.85},"DE":{"eic":"10Y1001A1001A82H","prices":[{"time":"22:00","hour":0,"price":108.89},{"time":"23:00","hour":1,"price":109.0},{"time":"00:00","hour":2,"price":99.8},{"time":"01:00","hour":3,"price":93.4},{"time":"02:00","hour":4,"price":98.7},{"time":"03:00","hour":5,"price":98.58},{"time":"04:00","hour":6,"price":96.0},{"time":"05:00","hour":7,"price":90.5},{"time":"06:00","hour":8,"price":93.3},{"time":"07:00","hour":9,"price":88.1},{"time":"08:00","hour":10,"price":92.56},{"time":"09:00","hour":11,"price":93.8},{"time":"10:00","hour":12,"price":92.06},{"time":"11:00","hour":13,"price":96.9},{"time":"12:00","hour":14,"price":94.9},{"time":"13:00","hour":15,"price":82.4},{"time":"14:00","hour":16,"price":85.7},{"time":"15:00","hour":17,"price":94.24},{"time":"16:00","hour":18,"price":87.5},{"time":"17:00","hour":19,"price":99.1},{"time":"18:00","hour":20,"price":84.2},{"time":"19:00","hour":21,"price":90.7},{"time":"20:00","hour":22,"price":94.7},{"time":"21:00","hour":23,"price":108.8},{"time":"22:00","hour":24,"price":96.3},{"time":"23:00","hour":25,"price":107.4},{"time":"00:00","hour":26,"price":116.2},{"time":"01:00","hour":27,"price":113.37},{"time":"02:00","hour":28,"price":123.5},{"time":"03:00","hour":29,"price":119.8},{"time":"04:00","hour":30,"price":104.4},{"time":"05:00","hour":31,"price":95.24},{"time":"06:00","hour":32,"price":139.97},{"time":"07:00","hour":33,"price":116.93},{"time":"08:00","hour":34,"price":101.3},{"time":"09:00","hour":35,"price":75.3},{"time":"10:00","hour":36,"price":125.0},{"time":"11:00","hour":37,"price":103.2},{"time":"12:00","hour":38,"price":87.0},{"time":"13:00","hour":39,"price":69.43},{"time":"14:00","hour":40,"price":114.93},{"time":"15:00","hour":41,"price":102.42},{"time":"16:00","hour":42,"price":76.65},{"time":"17:00","hour":43,"price":55.6},{"time":"18:00","hour":44,"price":101.34},{"time":"19:00","hour":45,"price":73.6},{"time":"20:00","hour":46,"price":64.3},{"time":"21:00","hour":47,"price":53.5},{"time":"22:00","hour":48,"price":77.0},{"time":"23:00","hour":49,"price":83.0},{"time":"00:00","hour":50,"price":60.0},{"time":"01:00","hour":51,"price":52.3},{"time":"02:00","hour":52,"price":70.0},{"time":"03:00","hour":53,"price":61.8},{"time":"04:00","hour":54,"price":56.8},{"time":"05:00","hour":55,"price":49.08},{"time":"06:00","hour":56,"price":54.2},{"time":"07:00","hour":57,"price":52.59},{"time":"08:00","hour":58,"price":50.1},{"time":"09:00","hour":59,"price":63.5},{"time":"10:00","hour":60,"price":48.4},{"time":"11:00","hour":61,"price":57.2},{"time":"12:00","hour":62,"price":65.1},{"time":"13:00","hour":63,"price":73.3},{"time":"14:00","hour":64,"price":48.44},{"time":"15:00","hour":65,"price":63.9},{"time":"16:00","hour":66,"price":76.3},{"time":"17:00","hour":67,"price":104.91},{"time":"18:00","hour":68,"price":59.6},{"time":"19:00","hour":69,"price":84.3},{"time":"20:00","hour":70,"price":93.6},{"time":"21:00","hour":71,"price":106.5},{"time":"22:00","hour":72,"price":60.06},{"time":"23:00","hour":73,"price":87.3},{"time":"00:00","hour":74,"price":114.47},{"time":"01:00","hour":75,"price":127.3},{"time":"02:00","hour":76,"price":80.02},{"time":"03:00","hour":77,"price":104.6},{"time":"04:00","hour":78,"price":118.9},{"time":"05:00","hour":79,"price":137.69},{"time":"06:00","hour":80,"price":119.7},{"time":"07:00","hour":81,"price":131.1},{"time":"08:00","hour":82,"price":137.5},{"time":"09:00","hour":83,"price":139.8},{"time":"10:00","hour":84,"price":159.7},{"time":"11:00","hour":85,"price":137.7},{"time":"12:00","hour":86,"price":132.87},{"time":"13:00","hour":87,"price":139.9},{"time":"14:00","hour":88,"price":147.49},{"time":"15:00","hour":89,"price":131.7},{"time":"16:00","hour":90,"price":127.9},{"time":"17:00","hour":91,"price":114.5},{"time":"18:00","hour":92,"price":120.5},{"time":"19:00","hour":93,"price":121.8},{"time":"20:00","hour":94,"price":106.69},{"time":"21:00","hour":95,"price":107.1},{"time":"22:00","hour":0,"price":103.76},{"time":"23:00","hour":1,"price":98.33},{"time":"00:00","hour":2,"price":89.96},{"time":"01:00","hour":3,"price":84.81},{"time":"02:00","hour":4,"price":85.76},{"time":"03:00","hour":5,"price":89.0},{"time":"04:00","hour":6,"price":104.05},{"time":"05:00","hour":7,"price":110.33},{"time":"06:00","hour":8,"price":105.92},{"time":"07:00","hour":9,"price":93.1},{"time":"08:00","hour":10,"price":85.0},{"time":"09:00","hour":11,"price":77.07},{"time":"10:00","hour":12,"price":70.17},{"time":"11:00","hour":13,"price":55.26},{"time":"12:00","hour":14,"price":49.78},{"time":"13:00","hour":15,"price":66.18},{"time":"14:00","hour":16,"price":74.79},{"time":"15:00","hour":17,"price":82.71},{"time":"16:00","hour":18,"price":94.98},{"time":"17:00","hour":19,"price":109.73},{"time":"18:00","hour":20,"price":120.75},{"time":"19:00","hour":21,"price":132.0},{"time":"20:00","hour":22,"price":125.07},{"time":"21:00","hour":23,"price":114.18},{"time":"22:00","hour":0,"price":121.9},{"time":"23:00","hour":1,"price":115.0},{"time":"00:00","hour":2,"price":99.37},{"time":"01:00","hour":3,"price":98.6},{"time":"02:00","hour":4,"price":103.2},{"time":"03:00","hour":5,"price":99.21},{"time":"04:00","hour":6,"price":102.1},{"time":"05:00","hour":7,"price":97.1},{"time":"06:00","hour":8,"price":94.4},{"time":"07:00","hour":9,"price":92.8},{"time":"08:00","hour":10,"price":102.04},{"time":"09:00","hour":11,"price":105.6},{"time":"10:00","hour":12,"price":96.1},{"time":"11:00","hour":13,"price":93.9},{"time":"12:00","hour":14,"price":104.04},{"time":"13:00","hour":15,"price":93.8},{"time":"14:00","hour":16,"price":88.0},{"time":"15:00","hour":17,"price":101.4},{"time":"16:00","hour":18,"price":100.51},{"time":"17:00","hour":19,"price":110.8},{"time":"18:00","hour":20,"price":97.9},{"time":"19:00","hour":21,"price":104.1},{"time":"20:00","hour":22,"price":108.1},{"time":"21:00","hour":23,"price":121.5},{"time":"22:00","hour":24,"price":111.9},{"time":"23:00","hour":25,"price":123.4},{"time":"00:00","hour":26,"price":126.27},{"time":"01:00","hour":27,"price":125.6},{"time":"02:00","hour":28,"price":129.92},{"time":"03:00","hour":29,"price":125.27},{"time":"04:00","hour":30,"price":121.48},{"time":"05:00","hour":31,"price":114.92},{"time":"06:00","hour":32,"price":144.97},{"time":"07:00","hour":33,"price":128.2},{"time":"08:00","hour":34,"price":107.49},{"time":"09:00","hour":35,"price":70.08},{"time":"10:00","hour":36,"price":125.8},{"time":"11:00","hour":37,"price":118.7},{"time":"12:00","hour":38,"price":89.9},{"time":"13:00","hour":39,"price":65.61},{"time":"14:00","hour":40,"price":124.91},{"time":"15:00","hour":41,"price":98.0},{"time":"16:00","hour":42,"price":83.2},{"time":"17:00","hour":43,"price":55.08},{"time":"18:00","hour":44,"price":101.5},{"time":"19:00","hour":45,"price":81.3},{"time":"20:00","hour":46,"price":72.57},{"time":"21:00","hour":47,"price":79.91},{"time":"22:00","hour":48,"price":99.91},{"time":"23:00","hour":49,"price":72.9},{"time":"00:00","hour":50,"price":64.6},{"time":"01:00","hour":51,"price":54.15},{"time":"02:00","hour":52,"price":77.21},{"time":"03:00","hour":53,"price":70.3},{"time":"04:00","hour":54,"price":64.0},{"time":"05:00","hour":55,"price":48.4},{"time":"06:00","hour":56,"price":59.5},{"time":"07:00","hour":57,"price":64.3},{"time":"08:00","hour":58,"price":67.7},{"time":"09:00","hour":59,"price":60.3},{"time":"10:00","hour":60,"price":45.07},{"time":"11:00","hour":61,"price":61.93},{"time":"12:00","hour":62,"price":79.6},{"time":"13:00","hour":63,"price":93.8},{"time":"14:00","hour":64,"price":55.5},{"time":"15:00","hour":65,"price":76.2},{"time":"16:00","hour":66,"price":91.3},{"time":"17:00","hour":67,"price":98.35},{"time":"18:00","hour":68,"price":55.7},{"time":"19:00","hour":69,"price":79.8},{"time":"20:00","hour":70,"price":107.5},{"time":"21:00","hour":71,"price":125.0},{"time":"22:00","hour":72,"price":55.05},{"time":"23:00","hour":73,"price":105.0},{"time":"00:00","hour":74,"price":132.4},{"time":"01:00","hour":75,"price":145.11},{"time":"02:00","hour":76,"price":91.03},{"time":"03:00","hour":77,"price":135.05},{"time":"04:00","hour":78,"price":145.02},{"time":"05:00","hour":79,"price":150.03},{"time":"06:00","hour":80,"price":162.3},{"time":"07:00","hour":81,"price":173.6},{"time":"08:00","hour":82,"price":177.2},{"time":"09:00","hour":83,"price":177.4},{"time":"10:00","hour":84,"price":189.99},{"time":"11:00","hour":85,"price":168.88},{"time":"12:00","hour":86,"price":153.0},{"time":"13:00","hour":87,"price":151.8},{"time":"14:00","hour":88,"price":139.8},{"time":"15:00","hour":89,"price":115.1},{"time":"16:00","hour":90,"price":137.8},{"time":"17:00","hour":91,"price":127.6},{"time":"18:00","hour":92,"price":119.74},{"time":"19:00","hour":93,"price":105.1},{"time":"20:00","hour":94,"price":122.7},{"time":"21:00","hour":95,"price":114.8},{"time":"22:00","hour":0,"price":106.8},{"time":"23:00","hour":1,"price":99.15},{"time":"00:00","hour":2,"price":95.36},{"time":"01:00","hour":3,"price":96.37},{"time":"02:00","hour":4,"price":98.66},{"time":"03:00","hour":5,"price":108.23},{"time":"04:00","hour":6,"price":115.92},{"time":"05:00","hour":7,"price":116.17},{"time":"06:00","hour":8,"price":109.39},{"time":"07:00","hour":9,"price":98.13},{"time":"08:00","hour":10,"price":84.98},{"time":"09:00","hour":11,"price":82.02},{"time":"10:00","hour":12,"price":80.0},{"time":"11:00","hour":13,"price":73.02},{"time":"12:00","hour":14,"price":71.2},{"time":"13:00","hour":15,"price":72.68},{"time":"14:00","hour":16,"price":79.99},{"time":"15:00","hour":17,"price":84.07},{"time":"16:00","hour":18,"price":99.92},{"time":"17:00","hour":19,"price":120.0},{"time":"18:00","hour":20,"price":146.55},{"time":"19:00","hour":21,"price":144.44},{"time":"20:00","hour":22,"price":125.88},{"time":"21:00","hour":23,"price":113.48}],"latest":{"time":"21:00","hour":23,"price":113.48},"avg":99.25,"min":45.07,"max":189.99},"FR":{"eic":"10YFR-RTE------C","prices":[{"time":"22:00","hour":0,"price":104.23},{"time":"23:00","hour":1,"price":98.38},{"time":"00:00","hour":2,"price":90.1},{"time":"01:00","hour":3,"price":83.77},{"time":"02:00","hour":4,"price":82.12},{"time":"03:00","hour":5,"price":89.16},{"time":"04:00","hour":6,"price":87.05},{"time":"05:00","hour":7,"price":101.62},{"time":"06:00","hour":8,"price":105.92},{"time":"07:00","hour":9,"price":93.1},{"time":"08:00","hour":10,"price":85.0},{"time":"09:00","hour":11,"price":77.07},{"time":"10:00","hour":12,"price":70.17},{"time":"11:00","hour":13,"price":56.14},{"time":"12:00","hour":14,"price":51.21},{"time":"13:00","hour":15,"price":66.56},{"time":"14:00","hour":16,"price":76.81},{"time":"15:00","hour":17,"price":84.36},{"time":"16:00","hour":18,"price":91.52},{"time":"17:00","hour":19,"price":108.66},{"time":"18:00","hour":20,"price":121.41},{"time":"19:00","hour":21,"price":125.8},{"time":"20:00","hour":22,"price":125.07},{"time":"21:00","hour":23,"price":114.18},{"time":"22:00","hour":0,"price":100.97},{"time":"23:00","hour":1,"price":92.22},{"time":"00:00","hour":2,"price":91.21},{"time":"01:00","hour":3,"price":82.52},{"time":"02:00","hour":4,"price":78.45},{"time":"03:00","hour":5,"price":84.31},{"time":"04:00","hour":6,"price":90.32},{"time":"05:00","hour":7,"price":105.08},{"time":"06:00","hour":8,"price":109.39},{"time":"07:00","hour":9,"price":90.64},{"time":"08:00","hour":10,"price":80.0},{"time":"09:00","hour":11,"price":81.58},{"time":"10:00","hour":12,"price":80.0},{"time":"11:00","hour":13,"price":73.02},{"time":"12:00","hour":14,"price":71.2},{"time":"13:00","hour":15,"price":72.68},{"time":"14:00","hour":16,"price":79.4},{"time":"15:00","hour":17,"price":83.22},{"time":"16:00","hour":18,"price":93.97},{"time":"17:00","hour":19,"price":108.1},{"time":"18:00","hour":20,"price":110.0},{"time":"19:00","hour":21,"price":119.39},{"time":"20:00","hour":22,"price":119.19},{"time":"21:00","hour":23,"price":111.65}],"latest":{"time":"21:00","hour":23,"price":111.65},"avg":91.62,"min":51.21,"max":125.8},"IT":{"eic":"10Y1001A1001A73I","prices":[{"time":"22:00","hour":0,"price":120.0},{"time":"02:00","hour":4,"price":114.03},{"time":"06:00","hour":8,"price":111.64},{"time":"10:00","hour":12,"price":110.0},{"time":"14:00","hour":16,"price":108.32},{"time":"18:00","hour":20,"price":111.02},{"time":"22:00","hour":24,"price":120.0},{"time":"02:00","hour":28,"price":125.53},{"time":"06:00","hour":32,"price":117.95},{"time":"10:00","hour":36,"price":115.53},{"time":"14:00","hour":40,"price":115.0},{"time":"18:00","hour":44,"price":111.64},{"time":"22:00","hour":48,"price":97.93},{"time":"02:00","hour":52,"price":100.28},{"time":"06:00","hour":56,"price":105.1},{"time":"10:00","hour":60,"price":110.0},{"time":"14:00","hour":64,"price":111.74},{"time":"18:00","hour":68,"price":115.0},{"time":"22:00","hour":72,"price":120.0},{"time":"02:00","hour":76,"price":135.0},{"time":"06:00","hour":80,"price":148.5},{"time":"10:00","hour":84,"price":135.81},{"time":"14:00","hour":88,"price":125.07},{"time":"18:00","hour":92,"price":115.85},{"time":"22:00","hour":0,"price":119.0},{"time":"02:00","hour":4,"price":112.04},{"time":"06:00","hour":8,"price":109.6},{"time":"10:00","hour":12,"price":108.65},{"time":"18:00","hour":20,"price":109.5},{"time":"22:00","hour":24,"price":120.32},{"time":"02:00","hour":28,"price":124.88},{"time":"06:00","hour":32,"price":125.0},{"time":"10:00","hour":36,"price":120.0},{"time":"14:00","hour":40,"price":109.55},{"time":"18:00","hour":44,"price":107.93},{"time":"22:00","hour":48,"price":98.94},{"time":"02:00","hour":52,"price":98.0},{"time":"06:00","hour":56,"price":105.1},{"time":"10:00","hour":60,"price":109.55},{"time":"14:00","hour":64,"price":119.23},{"time":"18:00","hour":68,"price":123.11},{"time":"22:00","hour":72,"price":129.0},{"time":"02:00","hour":76,"price":141.86},{"time":"06:00","hour":80,"price":150.0},{"time":"10:00","hour":84,"price":145.42},{"time":"14:00","hour":88,"price":132.25},{"time":"18:00","hour":92,"price":130.0}],"latest":{"time":"18:00","hour":92,"price":130.0},"avg":118.08,"min":97.93,"max":150.0},"NL":{"eic":"10YNL----------L","prices":[{"time":"22:00","hour":0,"price":103.91},{"time":"23:00","hour":1,"price":98.42},{"time":"00:00","hour":2,"price":90.04},{"time":"01:00","hour":3,"price":85.2},{"time":"02:00","hour":4,"price":86.49},{"time":"03:00","hour":5,"price":89.24},{"time":"04:00","hour":6,"price":104.36},{"time":"05:00","hour":7,"price":109.94},{"time":"06:00","hour":8,"price":105.92},{"time":"07:00","hour":9,"price":93.1},{"time":"08:00","hour":10,"price":85.0},{"time":"09:00","hour":11,"price":77.07},{"time":"10:00","hour":12,"price":70.17},{"time":"11:00","hour":13,"price":55.48},{"time":"12:00","hour":14,"price":50.23},{"time":"13:00","hour":15,"price":66.29},{"time":"14:00","hour":16,"price":75.29},{"time":"15:00","hour":17,"price":82.93},{"time":"16:00","hour":18,"price":96.59},{"time":"17:00","hour":19,"price":111.17},{"time":"18:00","hour":20,"price":122.01},{"time":"19:00","hour":21,"price":133.12},{"time":"20:00","hour":22,"price":125.07},{"time":"21:00","hour":23,"price":114.18},{"time":"22:00","hour":0,"price":107.74},{"time":"23:00","hour":1,"price":98.62},{"time":"00:00","hour":2,"price":95.72},{"time":"01:00","hour":3,"price":95.3},{"time":"02:00","hour":4,"price":97.06},{"time":"03:00","hour":5,"price":106.47},{"time":"04:00","hour":6,"price":112.66},{"time":"05:00","hour":7,"price":113.6},{"time":"06:00","hour":8,"price":109.39},{"time":"07:00","hour":9,"price":99.21},{"time":"08:00","hour":10,"price":85.63},{"time":"09:00","hour":11,"price":82.08},{"time":"10:00","hour":12,"price":80.0},{"time":"11:00","hour":13,"price":73.02},{"time":"12:00","hour":14,"price":71.2},{"time":"13:00","hour":15,"price":72.68},{"time":"14:00","hour":16,"price":80.55},{"time":"15:00","hour":17,"price":84.68},{"time":"16:00","hour":18,"price":99.78},{"time":"17:00","hour":19,"price":120.28},{"time":"18:00","hour":20,"price":146.55},{"time":"19:00","hour":21,"price":147.0},{"time":"20:00","hour":22,"price":126.88},{"time":"21:00","hour":23,"price":113.93}],"latest":{"time":"21:00","hour":23,"price":113.93},"avg":96.9,"min":50.23,"max":147.0},"BE":{"eic":"10YBE----------2","prices":[{"time":"22:00","hour":0,"price":104.02},{"time":"23:00","hour":1,"price":98.48},{"time":"00:00","hour":2,"price":90.1},{"time":"01:00","hour":3,"price":85.34},{"time":"02:00","hour":4,"price":86.61},{"time":"03:00","hour":5,"price":89.41},{"time":"04:00","hour":6,"price":99.35},{"time":"05:00","hour":7,"price":105.71},{"time":"06:00","hour":8,"price":105.92},{"time":"07:00","hour":9,"price":93.1},{"time":"08:00","hour":10,"price":85.0},{"time":"09:00","hour":11,"price":77.07},{"time":"10:00","hour":12,"price":70.17},{"time":"11:00","hour":13,"price":55.73},{"time":"12:00","hour":14,"price":50.6},{"time":"13:00","hour":15,"price":66.39},{"time":"14:00","hour":16,"price":75.8},{"time":"15:00","hour":17,"price":83.45},{"time":"16:00","hour":18,"price":97.01},{"time":"17:00","hour":19,"price":111.59},{"time":"18:00","hour":20,"price":122.45},{"time":"19:00","hour":21,"price":132.96},{"time":"20:00","hour":22,"price":125.07},{"time":"21:00","hour":23,"price":114.18},{"time":"22:00","hour":0,"price":107.56},{"time":"23:00","hour":1,"price":95.34},{"time":"00:00","hour":2,"price":95.0},{"time":"01:00","hour":3,"price":88.76},{"time":"02:00","hour":4,"price":87.57},{"time":"03:00","hour":5,"price":95.11},{"time":"04:00","hour":6,"price":101.61},{"time":"05:00","hour":7,"price":110.05},{"time":"06:00","hour":8,"price":109.39},{"time":"07:00","hour":9,"price":98.98},{"time":"08:00","hour":10,"price":85.53},{"time":"09:00","hour":11,"price":82.07},{"time":"10:00","hour":12,"price":80.0},{"time":"11:00","hour":13,"price":73.02},{"time":"12:00","hour":14,"price":71.2},{"time":"13:00","hour":15,"price":72.68},{"time":"14:00","hour":16,"price":80.42},{"time":"15:00","hour":17,"price":84.56},{"time":"16:00","hour":18,"price":96.6},{"time":"17:00","hour":19,"price":120.28},{"time":"18:00","hour":20,"price":146.55},{"time":"19:00","hour":21,"price":144.44},{"time":"20:00","hour":22,"price":126.62},{"time":"21:00","hour":23,"price":113.87}],"latest":{"time":"21:00","hour":23,"price":113.87},"avg":95.68,"min":50.6,"max":146.55},"AT":{"eic":"10YAT-APG------L","prices":[{"time":"22:00","hour":0,"price":138.63},{"time":"23:00","hour":1,"price":106.92},{"time":"00:00","hour":2,"price":96.61},{"time":"01:00","hour":3,"price":76.64},{"time":"02:00","hour":4,"price":116.36},{"time":"03:00","hour":5,"price":104.96},{"time":"04:00","hour":6,"price":101.64},{"time":"05:00","hour":7,"price":85.03},{"time":"06:00","hour":8,"price":104.99},{"time":"07:00","hour":9,"price":99.99},{"time":"08:00","hour":10,"price":99.73},{"time":"09:00","hour":11,"price":83.65},{"time":"10:00","hour":12,"price":100.0},{"time":"11:00","hour":13,"price":94.98},{"time":"12:00","hour":14,"price":90.0},{"time":"13:00","hour":15,"price":89.99},{"time":"14:00","hour":16,"price":78.84},{"time":"15:00","hour":17,"price":89.97},{"time":"16:00","hour":18,"price":94.95},{"time":"17:00","hour":19,"price":109.62},{"time":"18:00","hour":20,"price":66.4},{"time":"19:00","hour":21,"price":79.37},{"time":"20:00","hour":22,"price":110.0},{"time":"21:00","hour":23,"price":144.26},{"time":"22:00","hour":24,"price":75.77},{"time":"23:00","hour":25,"price":95.05},{"time":"00:00","hour":26,"price":124.89},{"time":"01:00","hour":27,"price":147.5},{"time":"02:00","hour":28,"price":77.65},{"time":"03:00","hour":29,"price":125.04},{"time":"04:00","hour":30,"price":126.4},{"time":"05:00","hour":31,"price":119.92},{"time":"06:00","hour":32,"price":139.99},{"time":"07:00","hour":33,"price":122.27},{"time":"08:00","hour":34,"price":100.08},{"time":"09:00","hour":35,"price":77.65},{"time":"10:00","hour":36,"price":114.43},{"time":"11:00","hour":37,"price":101.64},{"time":"12:00","hour":38,"price":109.95},{"time":"13:00","hour":39,"price":77.65},{"time":"14:00","hour":40,"price":165.16},{"time":"15:00","hour":41,"price":84.96},{"time":"16:00","hour":42,"price":66.8},{"time":"17:00","hour":43,"price":35.09},{"time":"18:00","hour":44,"price":99.9},{"time":"19:00","hour":45,"price":76.64},{"time":"20:00","hour":46,"price":54.93},{"time":"21:00","hour":47,"price":51.64},{"time":"22:00","hour":48,"price":87.01},{"time":"23:00","hour":49,"price":68.18},{"time":"00:00","hour":50,"price":44.97},{"time":"01:00","hour":51,"price":40.65},{"time":"02:00","hour":52,"price":80.56},{"time":"03:00","hour":53,"price":59.95},{"time":"04:00","hour":54,"price":51.64},{"time":"05:00","hour":55,"price":38.65},{"time":"06:00","hour":56,"price":54.67},{"time":"07:00","hour":57,"price":51.64},{"time":"08:00","hour":58,"price":77.65},{"time":"09:00","hour":59,"price":51.64},{"time":"10:00","hour":60,"price":98.74},{"time":"11:00","hour":61,"price":99.7},{"time":"12:00","hour":62,"price":40.98},{"time":"13:00","hour":63,"price":51.6},{"time":"14:00","hour":64,"price":30.0},{"time":"15:00","hour":65,"price":65.0},{"time":"16:00","hour":66,"price":96.6},{"time":"17:00","hour":67,"price":110.0},{"time":"18:00","hour":68,"price":59.95},{"time":"19:00","hour":69,"price":77.65},{"time":"20:00","hour":70,"price":90.05},{"time":"21:00","hour":71,"price":127.23},{"time":"22:00","hour":72,"price":58.94},{"time":"23:00","hour":73,"price":83.56},{"time":"00:00","hour":74,"price":116.41},{"time":"01:00","hour":75,"price":145.08},{"time":"02:00","hour":76,"price":76.64},{"time":"03:00","hour":77,"price":110.0},{"time":"04:00","hour":78,"price":133.09},{"time":"05:00","hour":79,"price":141.47},{"time":"06:00","hour":80,"price":101.64},{"time":"07:00","hour":81,"price":114.84},{"time":"08:00","hour":82,"price":148.19},{"time":"09:00","hour":83,"price":147.33},{"time":"10:00","hour":84,"price":155.01},{"time":"11:00","hour":85,"price":146.61},{"time":"12:00","hour":86,"price":110.0},{"time":"13:00","hour":87,"price":93.13},{"time":"14:00","hour":88,"price":142.09},{"time":"15:00","hour":89,"price":118.6},{"time":"16:00","hour":90,"price":110.0},{"time":"17:00","hour":91,"price":101.64},{"time":"18:00","hour":92,"price":149.91},{"time":"19:00","hour":93,"price":111.58},{"time":"20:00","hour":94,"price":101.64},{"time":"21:00","hour":95,"price":90.08},{"time":"22:00","hour":0,"price":101.56},{"time":"23:00","hour":1,"price":99.8},{"time":"00:00","hour":2,"price":91.38},{"time":"01:00","hour":3,"price":88.43},{"time":"02:00","hour":4,"price":89.07},{"time":"03:00","hour":5,"price":93.06},{"time":"04:00","hour":6,"price":99.55},{"time":"05:00","hour":7,"price":105.88},{"time":"06:00","hour":8,"price":105.92},{"time":"07:00","hour":9,"price":93.1},{"time":"08:00","hour":10,"price":85.0},{"time":"09:00","hour":11,"price":77.07},{"time":"10:00","hour":12,"price":70.17},{"time":"11:00","hour":13,"price":61.08},{"time":"12:00","hour":14,"price":53.77},{"time":"13:00","hour":15,"price":67.91},{"time":"14:00","hour":16,"price":72.09},{"time":"15:00","hour":17,"price":81.21},{"time":"16:00","hour":18,"price":108.09},{"time":"17:00","hour":19,"price":121.44},{"time":"18:00","hour":20,"price":132.04},{"time":"19:00","hour":21,"price":133.09},{"time":"20:00","hour":22,"price":125.07},{"time":"21:00","hour":23,"price":114.18},{"time":"22:00","hour":0,"price":132.89},{"time":"23:00","hour":1,"price":110.0},{"time":"00:00","hour":2,"price":100.05},{"time":"01:00","hour":3,"price":81.85},{"time":"02:00","hour":4,"price":119.49},{"time":"03:00","hour":5,"price":100.05},{"time":"04:00","hour":6,"price":95.01},{"time":"05:00","hour":7,"price":87.85},{"time":"06:00","hour":8,"price":112.94},{"time":"07:00","hour":9,"price":95.1},{"time":"08:00","hour":10,"price":97.6},{"time":"09:00","hour":11,"price":90.05},{"time":"10:00","hour":12,"price":95.09},{"time":"11:00","hour":13,"price":95.05},{"time":"12:00","hour":14,"price":95.08},{"time":"13:00","hour":15,"price":107.46},{"time":"14:00","hour":16,"price":90.07},{"time":"15:00","hour":17,"price":95.01},{"time":"16:00","hour":18,"price":95.07},{"time":"17:00","hour":19,"price":115.85},{"time":"18:00","hour":20,"price":63.86},{"time":"19:00","hour":21,"price":95.06},{"time":"20:00","hour":22,"price":115.04},{"time":"21:00","hour":23,"price":146.04},{"time":"22:00","hour":24,"price":62.85},{"time":"23:00","hour":25,"price":110.0},{"time":"00:00","hour":26,"price":125.08},{"time":"01:00","hour":27,"price":146.07},{"time":"02:00","hour":28,"price":91.85},{"time":"03:00","hour":29,"price":110.0},{"time":"04:00","hour":30,"price":120.96},{"time":"05:00","hour":31,"price":134.92},{"time":"06:00","hour":32,"price":141.74},{"time":"07:00","hour":33,"price":121.41},{"time":"08:00","hour":34,"price":105.01},{"time":"09:00","hour":35,"price":70.01},{"time":"10:00","hour":36,"price":135.1},{"time":"11:00","hour":37,"price":110.04},{"time":"12:00","hour":38,"price":87.67},{"time":"13:00","hour":39,"price":60.01},{"time":"14:00","hour":40,"price":132.84},{"time":"15:00","hour":41,"price":99.95},{"time":"16:00","hour":42,"price":63.86},{"time":"17:00","hour":43,"price":43.35},{"time":"18:00","hour":44,"price":300.0},{"time":"19:00","hour":45,"price":87.85},{"time":"20:00","hour":46,"price":60.82},{"time":"21:00","hour":47,"price":-100.0},{"time":"22:00","hour":48,"price":110.0},{"time":"23:00","hour":49,"price":63.86},{"time":"00:00","hour":50,"price":62.85},{"time":"01:00","hour":51,"price":46.09},{"time":"02:00","hour":52,"price":76.58},{"time":"03:00","hour":53,"price":63.86},{"time":"06:00","hour":56,"price":48.98},{"time":"07:00","hour":57,"price":55.0},{"time":"08:00","hour":58,"price":74.95},{"time":"09:00","hour":59,"price":89.1},{"time":"10:00","hour":60,"price":34.98},{"time":"11:00","hour":61,"price":62.85},{"time":"12:00","hour":62,"price":75.02},{"time":"13:00","hour":63,"price":110.0},{"time":"14:00","hour":64,"price":62.7},{"time":"15:00","hour":65,"price":64.96},{"time":"16:00","hour":66,"price":87.85},{"time":"17:00","hour":67,"price":110.0},{"time":"18:00","hour":68,"price":50.09},{"time":"19:00","hour":69,"price":70.02},{"time":"20:00","hour":70,"price":110.0},{"time":"21:00","hour":71,"price":140.01},{"time":"22:00","hour":72,"price":63.86},{"time":"23:00","hour":73,"price":110.0},{"time":"00:00","hour":74,"price":127.66},{"time":"01:00","hour":75,"price":136.89},{"time":"02:00","hour":76,"price":145.03},{"time":"03:00","hour":77,"price":158.45},{"time":"04:00","hour":78,"price":110.0},{"time":"06:00","hour":80,"price":165.09},{"time":"07:00","hour":81,"price":131.68},{"time":"08:00","hour":82,"price":165.0},{"time":"09:00","hour":83,"price":136.23},{"time":"10:00","hour":84,"price":178.0},{"time":"11:00","hour":85,"price":165.43},{"time":"12:00","hour":86,"price":111.8},{"time":"13:00","hour":87,"price":134.37},{"time":"14:00","hour":88,"price":170.03},{"time":"15:00","hour":89,"price":165.06},{"time":"16:00","hour":90,"price":110.0},{"time":"17:00","hour":91,"price":77.97},{"time":"18:00","hour":92,"price":160.06},{"time":"19:00","hour":93,"price":135.06},{"time":"20:00","hour":94,"price":110.0},{"time":"21:00","hour":95,"price":74.78},{"time":"22:00","hour":0,"price":106.98},{"time":"23:00","hour":1,"price":98.86},{"time":"00:00","hour":2,"price":95.61},{"time":"01:00","hour":3,"price":94.85},{"time":"02:00","hour":4,"price":95.97},{"time":"03:00","hour":5,"price":105.1},{"time":"04:00","hour":6,"price":113.99},{"time":"05:00","hour":7,"price":114.58},{"time":"06:00","hour":8,"price":109.39},{"time":"07:00","hour":9,"price":96.81},{"time":"08:00","hour":10,"price":84.08},{"time":"09:00","hour":11,"price":81.98},{"time":"10:00","hour":12,"price":80.0},{"time":"11:00","hour":13,"price":73.02},{"time":"12:00","hour":14,"price":71.2},{"time":"13:00","hour":15,"price":72.68},{"time":"14:00","hour":16,"price":80.04},{"time":"15:00","hour":17,"price":84.08},{"time":"16:00","hour":18,"price":91.15},{"time":"17:00","hour":19,"price":111.09},{"time":"18:00","hour":20,"price":138.8},{"time":"19:00","hour":21,"price":139.5},{"time":"20:00","hour":22,"price":122.58},{"time":"21:00","hour":23,"price":105.94}],"latest":{"time":"21:00","hour":23,"price":105.94},"avg":98.73,"min":-100.0,"max":300.0},"CH":{"eic":"10YCH-SWISSGRIDZ","prices":[{"time":"22:00","hour":0,"price":105.7},{"time":"23:00","hour":1,"price":101.0},{"time":"00:00","hour":2,"price":94.2},{"time":"01:00","hour":3,"price":92.49},{"time":"02:00","hour":4,"price":92.11},{"time":"03:00","hour":5,"price":96.33},{"time":"04:00","hour":6,"price":104.65},{"time":"05:00","hour":7,"price":111.31},{"time":"06:00","hour":8,"price":108.6},{"time":"07:00","hour":9,"price":97.41},{"time":"08:00","hour":10,"price":84.47},{"time":"09:00","hour":11,"price":78.19},{"time":"10:00","hour":12,"price":66.3},{"time":"11:00","hour":13,"price":59.48},{"time":"12:00","hour":14,"price":54.07},{"time":"13:00","hour":15,"price":65.73},{"time":"14:00","hour":16,"price":76.01},{"time":"15:00","hour":17,"price":84.86},{"time":"16:00","hour":18,"price":101.5},{"time":"17:00","hour":19,"price":109.0},{"time":"18:00","hour":20,"price":125.03},{"time":"19:00","hour":21,"price":129.4},{"time":"20:00","hour":22,"price":123.56},{"time":"21:00","hour":23,"price":111.01},{"time":"22:00","hour":0,"price":109.39},{"time":"23:00","hour":1,"price":103.91},{"time":"00:00","hour":2,"price":100.64},{"time":"01:00","hour":3,"price":98.99},{"time":"02:00","hour":4,"price":101.09},{"time":"03:00","hour":5,"price":105.09},{"time":"04:00","hour":6,"price":116.95},{"time":"05:00","hour":7,"price":116.55},{"time":"06:00","hour":8,"price":114.29},{"time":"07:00","hour":9,"price":103.09},{"time":"08:00","hour":10,"price":89.29},{"time":"09:00","hour":11,"price":81.84},{"time":"10:00","hour":12,"price":75.25},{"time":"11:00","hour":13,"price":67.96},{"time":"12:00","hour":14,"price":62.96},{"time":"13:00","hour":15,"price":70.97},{"time":"14:00","hour":16,"price":80.01},{"time":"15:00","hour":17,"price":89.17},{"time":"16:00","hour":18,"price":106.26},{"time":"17:00","hour":19,"price":116.52},{"time":"18:00","hour":20,"price":124.13},{"time":"19:00","hour":21,"price":123.08},{"time":"20:00","hour":22,"price":127.0},{"time":"21:00","hour":23,"price":114.53}],"latest":{"time":"21:00","hour":23,"price":114.53},"avg":97.32,"min":54.07,"max":129.4},"PL":{"eic":"10YPL-AREA-----S","prices":[{"time":"22:00","hour":0,"price":108.16},{"time":"23:00","hour":1,"price":104.04},{"time":"00:00","hour":2,"price":95.54},{"time":"01:00","hour":3,"price":99.53},{"time":"02:00","hour":4,"price":100.68},{"time":"03:00","hour":5,"price":104.77},{"time":"04:00","hour":6,"price":121.7},{"time":"05:00","hour":7,"price":123.37},{"time":"06:00","hour":8,"price":105.92},{"time":"07:00","hour":9,"price":117.59},{"time":"08:00","hour":10,"price":110.98},{"time":"09:00","hour":11,"price":108.57},{"time":"10:00","hour":12,"price":102.52},{"time":"11:00","hour":13,"price":106.82},{"time":"12:00","hour":14,"price":111.51},{"time":"13:00","hour":15,"price":114.57},{"time":"14:00","hour":16,"price":113.56},{"time":"15:00","hour":17,"price":118.77},{"time":"16:00","hour":18,"price":152.27},{"time":"17:00","hour":19,"price":170.93},{"time":"18:00","hour":20,"price":182.37},{"time":"19:00","hour":21,"price":140.94},{"time":"20:00","hour":22,"price":125.07},{"time":"21:00","hour":23,"price":114.18},{"time":"22:00","hour":0,"price":111.05},{"time":"23:00","hour":1,"price":101.44},{"time":"00:00","hour":2,"price":98.72},{"time":"01:00","hour":3,"price":97.23},{"time":"02:00","hour":4,"price":98.0},{"time":"03:00","hour":5,"price":107.68},{"time":"04:00","hour":6,"price":121.0},{"time":"05:00","hour":7,"price":115.86},{"time":"06:00","hour":8,"price":109.4},{"time":"07:00","hour":9,"price":97.8},{"time":"08:00","hour":10,"price":87.31},{"time":"09:00","hour":11,"price":83.97},{"time":"10:00","hour":12,"price":81.26},{"time":"11:00","hour":13,"price":85.35},{"time":"12:00","hour":14,"price":87.68},{"time":"13:00","hour":15,"price":91.61},{"time":"14:00","hour":16,"price":94.62},{"time":"15:00","hour":17,"price":95.3},{"time":"16:00","hour":18,"price":117.67},{"time":"17:00","hour":19,"price":131.44},{"time":"18:00","hour":20,"price":154.98},{"time":"19:00","hour":21,"price":148.65},{"time":"20:00","hour":22,"price":127.32},{"time":"21:00","hour":23,"price":116.45}],"latest":{"time":"21:00","hour":23,"price":116.45},"avg":112.84,"min":81.26,"max":182.37},"FI":{"eic":"10YFI-1--------U","prices":[{"time":"22:00","hour":0,"price":4.37},{"time":"23:00","hour":1,"price":3.66},{"time":"00:00","hour":2,"price":3.07},{"time":"01:00","hour":3,"price":3.34},{"time":"02:00","hour":4,"price":3.42},{"time":"03:00","hour":5,"price":4.5},{"time":"04:00","hour":6,"price":6.96},{"time":"05:00","hour":7,"price":18.57},{"time":"06:00","hour":8,"price":19.69},{"time":"07:00","hour":9,"price":14.86},{"time":"08:00","hour":10,"price":11.94},{"time":"09:00","hour":11,"price":11.45},{"time":"10:00","hour":12,"price":10.87},{"time":"11:00","hour":13,"price":11.04},{"time":"12:00","hour":14,"price":11.11},{"time":"13:00","hour":15,"price":12.98},{"time":"14:00","hour":16,"price":17.62},{"time":"15:00","hour":17,"price":21.95},{"time":"16:00","hour":18,"price":23.14},{"time":"17:00","hour":19,"price":16.65},{"time":"18:00","hour":20,"price":12.23},{"time":"19:00","hour":21,"price":9.13},{"time":"20:00","hour":22,"price":7.95},{"time":"21:00","hour":23,"price":6.17},{"time":"22:00","hour":0,"price":4.58},{"time":"23:00","hour":1,"price":4.47},{"time":"00:00","hour":2,"price":5.58},{"time":"01:00","hour":3,"price":6.1},{"time":"02:00","hour":4,"price":7.57},{"time":"03:00","hour":5,"price":11.21},{"time":"04:00","hour":6,"price":15.92},{"time":"05:00","hour":7,"price":31.81},{"time":"06:00","hour":8,"price":26.54},{"time":"07:00","hour":9,"price":15.54},{"time":"08:00","hour":10,"price":18.09},{"time":"09:00","hour":11,"price":19.36},{"time":"10:00","hour":12,"price":18.65},{"time":"11:00","hour":13,"price":17.01},{"time":"12:00","hour":14,"price":17.45},{"time":"13:00","hour":15,"price":18.16},{"time":"14:00","hour":16,"price":20.25},{"time":"15:00","hour":17,"price":21.74},{"time":"16:00","hour":18,"price":26.76},{"time":"17:00","hour":19,"price":27.99},{"time":"18:00","hour":20,"price":22.07},{"time":"19:00","hour":21,"price":11.66},{"time":"20:00","hour":22,"price":6.88},{"time":"21:00","hour":23,"price":4.99}],"latest":{"time":"21:00","hour":23,"price":4.99},"avg":13.48,"min":3.07,"max":31.81},"GR":{"eic":"10YGR-HTSO-----Y","prices":[{"time":"22:00","hour":0,"price":120.0},{"time":"23:00","hour":1,"price":120.34},{"time":"00:00","hour":2,"price":111.64},{"time":"01:00","hour":3,"price":110.0},{"time":"02:00","hour":4,"price":108.32},{"time":"03:00","hour":5,"price":111.02},{"time":"04:00","hour":6,"price":120.0},{"time":"05:00","hour":7,"price":125.53},{"time":"06:00","hour":8,"price":105.92},{"time":"07:00","hour":9,"price":93.1},{"time":"08:00","hour":10,"price":85.0},{"time":"09:00","hour":11,"price":77.07},{"time":"10:00","hour":12,"price":70.17},{"time":"11:00","hour":13,"price":63.0},{"time":"13:00","hour":15,"price":68.99},{"time":"14:00","hour":16,"price":104.37},{"time":"15:00","hour":17,"price":115.0},{"time":"16:00","hour":18,"price":123.04},{"time":"17:00","hour":19,"price":141.33},{"time":"18:00","hour":20,"price":153.49},{"time":"19:00","hour":21,"price":135.81},{"time":"20:00","hour":22,"price":125.08},{"time":"21:00","hour":23,"price":114.18},{"time":"22:00","hour":0,"price":108.28},{"time":"23:00","hour":1,"price":99.67},{"time":"00:00","hour":2,"price":96.61},{"time":"01:00","hour":3,"price":95.59},{"time":"02:00","hour":4,"price":96.58},{"time":"03:00","hour":5,"price":105.87},{"time":"04:00","hour":6,"price":116.22},{"time":"05:00","hour":7,"price":115.09},{"time":"06:00","hour":8,"price":108.43},{"time":"07:00","hour":9,"price":87.25},{"time":"08:00","hour":10,"price":70.27},{"time":"09:00","hour":11,"price":81.99},{"time":"10:00","hour":12,"price":80.0},{"time":"11:00","hour":13,"price":73.02},{"time":"12:00","hour":14,"price":71.2},{"time":"13:00","hour":15,"price":72.68},{"time":"14:00","hour":16,"price":104.26},{"time":"15:00","hour":17,"price":108.79},{"time":"16:00","hour":18,"price":129.0},{"time":"17:00","hour":19,"price":141.86},{"time":"18:00","hour":20,"price":166.84},{"time":"19:00","hour":21,"price":163.35},{"time":"20:00","hour":22,"price":132.25},{"time":"21:00","hour":23,"price":126.24}],"latest":{"time":"21:00","hour":23,"price":126.24},"avg":107.53,"min":63.0,"max":166.84},"IE":{"eic":"10Y1001A1001A59C","prices":[{"time":"22:00","hour":0,"price":119.75},{"time":"23:00","hour":1,"price":107.22},{"time":"00:00","hour":2,"price":96.84},{"time":"01:00","hour":3,"price":90.99},{"time":"02:00","hour":4,"price":88.66},{"time":"03:00","hour":5,"price":87.61},{"time":"04:00","hour":6,"price":91.94},{"time":"05:00","hour":7,"price":105.72},{"time":"06:00","hour":8,"price":116.67},{"time":"07:00","hour":9,"price":111.53},{"time":"08:00","hour":10,"price":105.0},{"time":"09:00","hour":11,"price":98.05},{"time":"10:00","hour":12,"price":92.24},{"time":"11:00","hour":13,"price":92.37},{"time":"12:00","hour":14,"price":85.47},{"time":"13:00","hour":15,"price":84.17},{"time":"14:00","hour":16,"price":82.8},{"time":"15:00","hour":17,"price":89.58},{"time":"16:00","hour":18,"price":98.04},{"time":"17:00","hour":19,"price":111.32},{"time":"18:00","hour":20,"price":122.9},{"time":"19:00","hour":21,"price":125.28},{"time":"20:00","hour":22,"price":122.51},{"time":"21:00","hour":23,"price":115.1},{"time":"22:00","hour":0,"price":104.83},{"time":"23:00","hour":1,"price":95.0},{"time":"00:00","hour":2,"price":92.62},{"time":"01:00","hour":3,"price":91.0},{"time":"04:00","hour":6,"price":94.45},{"time":"05:00","hour":7,"price":114.2},{"time":"06:00","hour":8,"price":121.57},{"time":"07:00","hour":9,"price":122.5},{"time":"08:00","hour":10,"price":115.63},{"time":"09:00","hour":11,"price":106.5},{"time":"10:00","hour":12,"price":101.34},{"time":"11:00","hour":13,"price":97.0},{"time":"12:00","hour":14,"price":93.37},{"time":"14:00","hour":16,"price":95.24},{"time":"15:00","hour":17,"price":103.89},{"time":"16:00","hour":18,"price":130.37},{"time":"17:00","hour":19,"price":155.0},{"time":"19:00","hour":21,"price":156.0},{"time":"20:00","hour":22,"price":166.5},{"time":"21:00","hour":23,"price":174.5}],"latest":{"time":"21:00","hour":23,"price":174.5},"avg":108.48,"min":82.8,"max":174.5},"RO":{"eic":"10YRO-TEL------P","prices":[{"time":"22:00","hour":0,"price":108.27},{"time":"23:00","hour":1,"price":101.16},{"time":"00:00","hour":2,"price":92.75},{"time":"01:00","hour":3,"price":91.98},{"time":"02:00","hour":4,"price":92.8},{"time":"03:00","hour":5,"price":96.85},{"time":"04:00","hour":6,"price":114.96},{"time":"05:00","hour":7,"price":119.55},{"time":"06:00","hour":8,"price":105.92},{"time":"07:00","hour":9,"price":93.1},{"time":"08:00","hour":10,"price":85.0},{"time":"09:00","hour":11,"price":77.07},{"time":"10:00","hour":12,"price":70.17},{"time":"11:00","hour":13,"price":63.0},{"time":"13:00","hour":15,"price":68.99},{"time":"14:00","hour":16,"price":104.37},{"time":"15:00","hour":17,"price":115.0},{"time":"16:00","hour":18,"price":123.04},{"time":"17:00","hour":19,"price":141.33},{"time":"18:00","hour":20,"price":153.49},{"time":"19:00","hour":21,"price":135.81},{"time":"20:00","hour":22,"price":125.07},{"time":"21:00","hour":23,"price":114.18},{"time":"22:00","hour":0,"price":108.28},{"time":"23:00","hour":1,"price":99.67},{"time":"00:00","hour":2,"price":96.61},{"time":"01:00","hour":3,"price":95.59},{"time":"02:00","hour":4,"price":96.58},{"time":"03:00","hour":5,"price":105.87},{"time":"04:00","hour":6,"price":116.22},{"time":"05:00","hour":7,"price":115.09},{"time":"06:00","hour":8,"price":108.43},{"time":"07:00","hour":9,"price":87.25},{"time":"08:00","hour":10,"price":70.27},{"time":"09:00","hour":11,"price":81.99},{"time":"10:00","hour":12,"price":80.0},{"time":"11:00","hour":13,"price":73.02},{"time":"12:00","hour":14,"price":71.2},{"time":"13:00","hour":15,"price":72.68},{"time":"14:00","hour":16,"price":104.26},{"time":"15:00","hour":17,"price":108.79},{"time":"16:00","hour":18,"price":129.0},{"time":"17:00","hour":19,"price":141.86},{"time":"18:00","hour":20,"price":166.84},{"time":"19:00","hour":21,"price":163.35},{"time":"20:00","hour":22,"price":132.25},{"time":"21:00","hour":23,"price":126.24}],"latest":{"time":"21:00","hour":23,"price":126.24},"avg":105.22,"min":63.0,"max":166.84},"BG":{"eic":"10YCA-BULGARIA-R","prices":[{"time":"22:00","hour":0,"price":108.27},{"time":"23:00","hour":1,"price":101.16},{"time":"00:00","hour":2,"price":92.75},{"time":"01:00","hour":3,"price":91.98},{"time":"02:00","hour":4,"price":92.8},{"time":"03:00","hour":5,"price":96.85},{"time":"04:00","hour":6,"price":114.96},{"time":"05:00","hour":7,"price":119.55},{"time":"06:00","hour":8,"price":105.92},{"time":"07:00","hour":9,"price":93.1},{"time":"08:00","hour":10,"price":85.0},{"time":"09:00","hour":11,"price":77.07},{"time":"10:00","hour":12,"price":70.17},{"time":"11:00","hour":13,"price":63.0},{"time":"13:00","hour":15,"price":68.99},{"time":"14:00","hour":16,"price":104.37},{"time":"15:00","hour":17,"price":115.0},{"time":"16:00","hour":18,"price":123.04},{"time":"17:00","hour":19,"price":141.33},{"time":"18:00","hour":20,"price":153.49},{"time":"19:00","hour":21,"price":135.81},{"time":"20:00","hour":22,"price":125.07},{"time":"21:00","hour":23,"price":114.18},{"time":"22:00","hour":0,"price":108.28},{"time":"23:00","hour":1,"price":99.67},{"time":"00:00","hour":2,"price":96.61},{"time":"01:00","hour":3,"price":95.59},{"time":"02:00","hour":4,"price":96.58},{"time":"03:00","hour":5,"price":105.87},{"time":"04:00","hour":6,"price":116.22},{"time":"05:00","hour":7,"price":115.09},{"time":"06:00","hour":8,"price":108.43},{"time":"07:00","hour":9,"price":87.25},{"time":"08:00","hour":10,"price":70.27},{"time":"09:00","hour":11,"price":81.99},{"time":"10:00","hour":12,"price":80.0},{"time":"11:00","hour":13,"price":73.02},{"time":"12:00","hour":14,"price":71.2},{"time":"13:00","hour":15,"price":72.68},{"time":"14:00","hour":16,"price":104.26},{"time":"15:00","hour":17,"price":108.79},{"time":"16:00","hour":18,"price":129.0},{"time":"17:00","hour":19,"price":141.86},{"time":"18:00","hour":20,"price":166.84},{"time":"19:00","hour":21,"price":163.35},{"time":"20:00","hour":22,"price":132.25},{"time":"21:00","hour":23,"price":126.24}],"latest":{"time":"21:00","hour":23,"price":126.24},"avg":105.22,"min":63.0,"max":166.84},"HU":{"eic":"10YHU-MAVIR----U","prices":[{"time":"22:00","hour":0,"price":107.32},{"time":"23:00","hour":1,"price":101.17},{"time":"00:00","hour":2,"price":92.75},{"time":"01:00","hour":3,"price":92.0},{"time":"02:00","hour":4,"price":92.81},{"time":"03:00","hour":5,"price":96.88},{"time":"04:00","hour":6,"price":113.62},{"time":"05:00","hour":7,"price":118.2},{"time":"06:00","hour":8,"price":105.92},{"time":"07:00","hour":9,"price":93.1},{"time":"08:00","hour":10,"price":85.0},{"time":"09:00","hour":11,"price":77.07},{"time":"10:00","hour":12,"price":70.17},{"time":"11:00","hour":13,"price":63.25},{"time":"12:00","hour":14,"price":62.45},{"time":"13:00","hour":15,"price":69.09},{"time":"14:00","hour":16,"price":103.17},{"time":"15:00","hour":17,"price":105.18},{"time":"16:00","hour":18,"price":122.96},{"time":"17:00","hour":19,"price":140.79},{"time":"18:00","hour":20,"price":152.72},{"time":"19:00","hour":21,"price":135.83},{"time":"20:00","hour":22,"price":125.07},{"time":"21:00","hour":23,"price":114.18},{"time":"22:00","hour":0,"price":108.34},{"time":"23:00","hour":1,"price":99.74},{"time":"00:00","hour":2,"price":96.65},{"time":"01:00","hour":3,"price":95.72},{"time":"02:00","hour":4,"price":96.76},{"time":"03:00","hour":5,"price":106.09},{"time":"04:00","hour":6,"price":116.41},{"time":"05:00","hour":7,"price":115.18},{"time":"06:00","hour":8,"price":109.45},{"time":"07:00","hour":9,"price":97.79},{"time":"08:00","hour":10,"price":85.26},{"time":"09:00","hour":11,"price":82.0},{"time":"10:00","hour":12,"price":80.0},{"time":"11:00","hour":13,"price":73.02},{"time":"12:00","hour":14,"price":71.2},{"time":"13:00","hour":15,"price":72.68},{"time":"14:00","hour":16,"price":102.35},{"time":"15:00","hour":17,"price":106.83},{"time":"16:00","hour":18,"price":129.67},{"time":"17:00","hour":19,"price":143.43},{"time":"18:00","hour":20,"price":171.09},{"time":"19:00","hour":21,"price":168.08},{"time":"20:00","hour":22,"price":133.38},{"time":"21:00","hour":23,"price":126.83}],"latest":{"time":"21:00","hour":23,"price":126.83},"avg":104.76,"min":62.45,"max":171.09},"CZ":{"eic":"10YCZ-CEPS-----N","prices":[{"time":"22:00","hour":0,"price":105.09},{"time":"23:00","hour":1,"price":100.09},{"time":"00:00","hour":2,"price":91.7},{"time":"01:00","hour":3,"price":89.3},{"time":"02:00","hour":4,"price":90.21},{"time":"03:00","hour":5,"price":93.89},{"time":"04:00","hour":6,"price":108.91},{"time":"05:00","hour":7,"price":114.11},{"time":"06:00","hour":8,"price":105.92},{"time":"07:00","hour":9,"price":93.1},{"time":"08:00","hour":10,"price":85.0},{"time":"09:00","hour":11,"price":77.07},{"time":"10:00","hour":12,"price":70.17},{"time":"11:00","hour":13,"price":67.76},{"time":"12:00","hour":14,"price":57.1},{"time":"13:00","hour":15,"price":71.34},{"time":"14:00","hour":16,"price":88.48},{"time":"15:00","hour":17,"price":94.73},{"time":"16:00","hour":18,"price":112.75},{"time":"17:00","hour":19,"price":128.76},{"time":"18:00","hour":20,"price":139.96},{"time":"19:00","hour":21,"price":134.5},{"time":"20:00","hour":22,"price":125.07},{"time":"21:00","hour":23,"price":114.18},{"time":"22:00","hour":0,"price":107.84},{"time":"23:00","hour":1,"price":99.69},{"time":"00:00","hour":2,"price":96.24},{"time":"01:00","hour":3,"price":96.29},{"time":"02:00","hour":4,"price":97.95},{"time":"03:00","hour":5,"price":107.46},{"time":"04:00","hour":6,"price":116.86},{"time":"05:00","hour":7,"price":115.82},{"time":"06:00","hour":8,"price":109.4},{"time":"07:00","hour":9,"price":97.77},{"time":"08:00","hour":10,"price":84.84},{"time":"09:00","hour":11,"price":82.01},{"time":"10:00","hour":12,"price":80.0},{"time":"11:00","hour":13,"price":73.02},{"time":"12:00","hour":14,"price":71.2},{"time":"13:00","hour":15,"price":72.68},{"time":"14:00","hour":16,"price":87.65},{"time":"15:00","hour":17,"price":91.87},{"time":"16:00","hour":18,"price":101.9},{"time":"17:00","hour":19,"price":120.0},{"time":"18:00","hour":20,"price":142.41},{"time":"19:00","hour":21,"price":139.5},{"time":"20:00","hour":22,"price":124.58},{"time":"21:00","hour":23,"price":111.94}],"latest":{"time":"21:00","hour":23,"price":111.94},"avg":99.75,"min":57.1,"max":142.41},"EE":{"eic":"10Y1001A1001A39I","prices":[{"time":"22:00","hour":0,"price":108.16},{"time":"23:00","hour":1,"price":104.04},{"time":"00:00","hour":2,"price":40.0},{"time":"01:00","hour":3,"price":6.1},{"time":"02:00","hour":4,"price":25.03},{"time":"03:00","hour":5,"price":104.77},{"time":"04:00","hour":6,"price":121.7},{"time":"05:00","hour":7,"price":18.57},{"time":"06:00","hour":8,"price":19.69},{"time":"07:00","hour":9,"price":14.86},{"time":"08:00","hour":10,"price":11.94},{"time":"09:00","hour":11,"price":11.45},{"time":"10:00","hour":12,"price":10.87},{"time":"11:00","hour":13,"price":11.04},{"time":"12:00","hour":14,"price":11.11},{"time":"13:00","hour":15,"price":12.98},{"time":"14:00","hour":16,"price":17.62},{"time":"15:00","hour":17,"price":21.95},{"time":"16:00","hour":18,"price":40.5},{"time":"17:00","hour":19,"price":148.61},{"time":"18:00","hour":20,"price":170.29},{"time":"19:00","hour":21,"price":61.94},{"time":"20:00","hour":22,"price":59.96},{"time":"21:00","hour":23,"price":6.16},{"time":"22:00","hour":0,"price":4.98},{"time":"00:00","hour":2,"price":5.58},{"time":"01:00","hour":3,"price":6.09},{"time":"02:00","hour":4,"price":7.57},{"time":"03:00","hour":5,"price":11.21},{"time":"04:00","hour":6,"price":15.92},{"time":"05:00","hour":7,"price":31.81},{"time":"06:00","hour":8,"price":26.54},{"time":"07:00","hour":9,"price":15.54},{"time":"08:00","hour":10,"price":18.09},{"time":"09:00","hour":11,"price":19.36},{"time":"10:00","hour":12,"price":18.65},{"time":"11:00","hour":13,"price":17.01},{"time":"12:00","hour":14,"price":17.45},{"time":"13:00","hour":15,"price":18.16},{"time":"14:00","hour":16,"price":20.25},{"time":"15:00","hour":17,"price":21.74},{"time":"16:00","hour":18,"price":63.56},{"time":"17:00","hour":19,"price":131.44},{"time":"18:00","hour":20,"price":148.71},{"time":"19:00","hour":21,"price":65.12},{"time":"20:00","hour":22,"price":62.31},{"time":"21:00","hour":23,"price":59.07}],"latest":{"time":"21:00","hour":23,"price":59.07},"avg":41.82,"min":4.98,"max":170.29},"LV":{"eic":"10YLV-1001A00074","prices":[{"time":"22:00","hour":0,"price":108.16},{"time":"23:00","hour":1,"price":104.04},{"time":"00:00","hour":2,"price":40.0},{"time":"01:00","hour":3,"price":6.1},{"time":"02:00","hour":4,"price":100.68},{"time":"03:00","hour":5,"price":104.77},{"time":"04:00","hour":6,"price":121.7},{"time":"05:00","hour":7,"price":123.37},{"time":"06:00","hour":8,"price":33.62},{"time":"07:00","hour":9,"price":30.64},{"time":"08:00","hour":10,"price":28.12},{"time":"09:00","hour":11,"price":26.83},{"time":"10:00","hour":12,"price":25.39},{"time":"11:00","hour":13,"price":23.84},{"time":"12:00","hour":14,"price":23.33},{"time":"13:00","hour":15,"price":25.75},{"time":"14:00","hour":16,"price":28.88},{"time":"15:00","hour":17,"price":32.1},{"time":"16:00","hour":18,"price":40.5},{"time":"17:00","hour":19,"price":148.61},{"time":"18:00","hour":20,"price":170.29},{"time":"19:00","hour":21,"price":61.94},{"time":"20:00","hour":22,"price":59.96},{"time":"21:00","hour":23,"price":58.61},{"time":"22:00","hour":0,"price":58.97},{"time":"23:00","hour":1,"price":57.45},{"time":"00:00","hour":2,"price":57.15},{"time":"01:00","hour":3,"price":55.71},{"time":"02:00","hour":4,"price":53.9},{"time":"03:00","hour":5,"price":55.36},{"time":"04:00","hour":6,"price":121.0},{"time":"05:00","hour":7,"price":103.94},{"time":"06:00","hour":8,"price":60.45},{"time":"07:00","hour":9,"price":59.79},{"time":"08:00","hour":10,"price":31.97},{"time":"09:00","hour":11,"price":32.43},{"time":"10:00","hour":12,"price":31.48},{"time":"11:00","hour":13,"price":28.76},{"time":"12:00","hour":14,"price":28.45},{"time":"13:00","hour":15,"price":29.47},{"time":"14:00","hour":16,"price":34.0},{"time":"15:00","hour":17,"price":36.03},{"time":"16:00","hour":18,"price":63.56},{"time":"17:00","hour":19,"price":131.44},{"time":"18:00","hour":20,"price":148.71},{"time":"19:00","hour":21,"price":65.12},{"time":"20:00","hour":22,"price":62.31},{"time":"21:00","hour":23,"price":59.07}],"latest":{"time":"21:00","hour":23,"price":59.07},"avg":62.37,"min":6.1,"max":170.29},"LT":{"eic":"10YLT-1001A0008Q","prices":[{"time":"22:00","hour":0,"price":108.16},{"time":"23:00","hour":1,"price":104.04},{"time":"00:00","hour":2,"price":40.0},{"time":"01:00","hour":3,"price":6.1},{"time":"02:00","hour":4,"price":100.68},{"time":"03:00","hour":5,"price":104.77},{"time":"04:00","hour":6,"price":121.7},{"time":"05:00","hour":7,"price":123.37},{"time":"06:00","hour":8,"price":33.62},{"time":"07:00","hour":9,"price":30.64},{"time":"08:00","hour":10,"price":28.12},{"time":"09:00","hour":11,"price":26.83},{"time":"10:00","hour":12,"price":25.39},{"time":"11:00","hour":13,"price":23.84},{"time":"12:00","hour":14,"price":23.33},{"time":"13:00","hour":15,"price":25.75},{"time":"14:00","hour":16,"price":28.88},{"time":"15:00","hour":17,"price":32.1},{"time":"16:00","hour":18,"price":40.5},{"time":"17:00","hour":19,"price":148.61},{"time":"18:00","hour":20,"price":170.29},{"time":"19:00","hour":21,"price":61.94},{"time":"20:00","hour":22,"price":59.96},{"time":"21:00","hour":23,"price":58.61},{"time":"22:00","hour":0,"price":58.97},{"time":"23:00","hour":1,"price":57.45},{"time":"00:00","hour":2,"price":57.15},{"time":"01:00","hour":3,"price":55.71},{"time":"02:00","hour":4,"price":53.9},{"time":"03:00","hour":5,"price":55.36},{"time":"04:00","hour":6,"price":121.0},{"time":"05:00","hour":7,"price":103.94},{"time":"06:00","hour":8,"price":60.45},{"time":"07:00","hour":9,"price":59.79},{"time":"08:00","hour":10,"price":31.97},{"time":"09:00","hour":11,"price":32.43},{"time":"10:00","hour":12,"price":31.48},{"time":"11:00","hour":13,"price":28.76},{"time":"12:00","hour":14,"price":28.45},{"time":"13:00","hour":15,"price":29.47},{"time":"14:00","hour":16,"price":34.0},{"time":"15:00","hour":17,"price":36.03},{"time":"16:00","hour":18,"price":63.56},{"time":"17:00","hour":19,"price":131.44},{"time":"18:00","hour":20,"price":148.71},{"time":"19:00","hour":21,"price":65.12},{"time":"20:00","hour":22,"price":62.31},{"time":"21:00","hour":23,"price":59.07}],"latest":{"time":"21:00","hour":23,"price":59.07},"avg":62.37,"min":6.1,"max":170.29},"NO":{"eic":"10YNO-1--------2, 10YNO-2--------T","prices":[{"time":"22:00","hour":0,"price":40.21},{"time":"02:00","hour":4,"price":38.45},{"time":"06:00","hour":8,"price":36.57},{"time":"10:00","hour":12,"price":36.37},{"time":"14:00","hour":16,"price":36.22},{"time":"18:00","hour":20,"price":37.15},{"time":"22:00","hour":24,"price":39.71},{"time":"02:00","hour":28,"price":61.41},{"time":"06:00","hour":32,"price":68.58},{"time":"10:00","hour":36,"price":67.12},{"time":"14:00","hour":40,"price":63.55},{"time":"18:00","hour":44,"price":59.86},{"time":"22:00","hour":48,"price":56.48},{"time":"02:00","hour":52,"price":51.78},{"time":"06:00","hour":56,"price":50.21},{"time":"10:00","hour":60,"price":54.6},{"time":"14:00","hour":64,"price":58.28},{"time":"18:00","hour":68,"price":61.3},{"time":"22:00","hour":72,"price":66.99},{"time":"02:00","hour":76,"price":68.67},{"time":"06:00","hour":80,"price":68.91},{"time":"10:00","hour":84,"price":68.98},{"time":"14:00","hour":88,"price":66.61},{"time":"18:00","hour":92,"price":65.51},{"time":"22:00","hour":0,"price":65.81},{"time":"02:00","hour":4,"price":64.59},{"time":"06:00","hour":8,"price":63.67},{"time":"10:00","hour":12,"price":62.42},{"time":"14:00","hour":16,"price":61.8},{"time":"18:00","hour":20,"price":62.87},{"time":"22:00","hour":24,"price":65.41},{"time":"02:00","hour":28,"price":63.98},{"time":"06:00","hour":32,"price":68.72},{"time":"10:00","hour":36,"price":68.16},{"time":"14:00","hour":40,"price":65.9},{"time":"18:00","hour":44,"price":65.34},{"time":"22:00","hour":48,"price":63.88},{"time":"02:00","hour":52,"price":58.38},{"time":"06:00","hour":56,"price":56.94},{"time":"10:00","hour":60,"price":58.61},{"time":"14:00","hour":64,"price":63.62},{"time":"18:00","hour":68,"price":65.49},{"time":"22:00","hour":72,"price":71.83},{"time":"02:00","hour":76,"price":78.83},{"time":"06:00","hour":80,"price":76.22},{"time":"10:00","hour":84,"price":72.38},{"time":"14:00","hour":88,"price":68.0},{"time":"18:00","hour":92,"price":65.75}],"latest":{"time":"18:00","hour":92,"price":65.75},"avg":60.46,"min":0.99,"max":98.44},"SE":{"eic":"10Y1001A1001A44P, 10Y1001A1001A46L","prices":[{"time":"22:00","hour":0,"price":4.78},{"time":"23:00","hour":1,"price":4.1},{"time":"00:00","hour":2,"price":3.06},{"time":"01:00","hour":3,"price":3.41},{"time":"02:00","hour":4,"price":3.42},{"time":"03:00","hour":5,"price":4.45},{"time":"04:00","hour":6,"price":6.96},{"time":"05:00","hour":7,"price":23.21},{"time":"06:00","hour":8,"price":24.07},{"time":"07:00","hour":9,"price":19.91},{"time":"08:00","hour":10,"price":17.46},{"time":"09:00","hour":11,"price":17.09},{"time":"10:00","hour":12,"price":16.23},{"time":"11:00","hour":13,"price":15.73},{"time":"12:00","hour":14,"price":15.62},{"time":"13:00","hour":15,"price":17.66},{"time":"14:00","hour":16,"price":21.26},{"time":"15:00","hour":17,"price":25.12},{"time":"16:00","hour":18,"price":26.75},{"time":"17:00","hour":19,"price":27.49},{"time":"18:00","hour":20,"price":24.53},{"time":"19:00","hour":21,"price":22.41},{"time":"20:00","hour":22,"price":21.24},{"time":"21:00","hour":23,"price":19.8},{"time":"22:00","hour":0,"price":18.71},{"time":"23:00","hour":1,"price":18.33},{"time":"00:00","hour":2,"price":19.08},{"time":"01:00","hour":3,"price":19.04},{"time":"02:00","hour":4,"price":19.8},{"time":"03:00","hour":5,"price":22.37},{"time":"04:00","hour":6,"price":26.37},{"time":"05:00","hour":7,"price":30.52},{"time":"06:00","hour":8,"price":30.77},{"time":"07:00","hour":9,"price":26.41},{"time":"08:00","hour":10,"price":22.13},{"time":"09:00","hour":11,"price":23.14},{"time":"10:00","hour":12,"price":22.44},{"time":"11:00","hour":13,"price":20.48},{"time":"12:00","hour":14,"price":20.66},{"time":"13:00","hour":15,"price":21.49},{"time":"14:00","hour":16,"price":24.8},{"time":"15:00","hour":17,"price":26.56},{"time":"16:00","hour":18,"price":31.51},{"time":"17:00","hour":19,"price":31.43},{"time":"18:00","hour":20,"price":27.73},{"time":"19:00","hour":21,"price":24.27},{"time":"20:00","hour":22,"price":20.84},{"time":"21:00","hour":23,"price":18.98}],"latest":{"time":"21:00","hour":23,"price":18.98},"avg":19.87,"min":3.06,"max":49.29},"DK":{"eic":"10YDK-1--------W, 10YDK-2--------M","prices":[{"time":"22:00","hour":0,"price":103.76},{"time":"23:00","hour":1,"price":98.33},{"time":"00:00","hour":2,"price":89.96},{"time":"01:00","hour":3,"price":84.81},{"time":"02:00","hour":4,"price":85.76},{"time":"03:00","hour":5,"price":89.0},{"time":"04:00","hour":6,"price":92.54},{"time":"05:00","hour":7,"price":110.32},{"time":"06:00","hour":8,"price":105.91},{"time":"07:00","hour":9,"price":93.09},{"time":"08:00","hour":10,"price":84.99},{"time":"09:00","hour":11,"price":77.06},{"time":"10:00","hour":12,"price":70.16},{"time":"11:00","hour":13,"price":55.25},{"time":"12:00","hour":14,"price":49.78},{"time":"13:00","hour":15,"price":66.18},{"time":"14:00","hour":16,"price":74.78},{"time":"15:00","hour":17,"price":82.7},{"time":"16:00","hour":18,"price":94.97},{"time":"17:00","hour":19,"price":109.73},{"time":"18:00","hour":20,"price":120.75},{"time":"19:00","hour":21,"price":132.0},{"time":"20:00","hour":22,"price":125.07},{"time":"21:00","hour":23,"price":114.18},{"time":"22:00","hour":0,"price":106.8},{"time":"23:00","hour":1,"price":99.15},{"time":"00:00","hour":2,"price":95.36},{"time":"01:00","hour":3,"price":96.37},{"time":"02:00","hour":4,"price":98.66},{"time":"03:00","hour":5,"price":108.23},{"time":"04:00","hour":6,"price":115.92},{"time":"05:00","hour":7,"price":116.17},{"time":"06:00","hour":8,"price":109.39},{"time":"07:00","hour":9,"price":98.12},{"time":"08:00","hour":10,"price":84.97},{"time":"09:00","hour":11,"price":82.01},{"time":"10:00","hour":12,"price":79.99},{"time":"11:00","hour":13,"price":73.01},{"time":"12:00","hour":14,"price":71.19},{"time":"13:00","hour":15,"price":72.67},{"time":"14:00","hour":16,"price":79.98},{"time":"15:00","hour":17,"price":84.06},{"time":"16:00","hour":18,"price":99.92},{"time":"17:00","hour":19,"price":120.0},{"time":"18:00","hour":20,"price":146.55},{"time":"19:00","hour":21,"price":144.44},{"time":"20:00","hour":22,"price":125.88},{"time":"21:00","hour":23,"price":113.48}],"latest":{"time":"21:00","hour":23,"price":113.48},"avg":96.53,"min":49.77,"max":146.55}}}